README.md
setup.py
TOPSIS_Shimantika_101803273.egg-info/PKG-INFO
TOPSIS_Shimantika_101803273.egg-info/SOURCES.txt
TOPSIS_Shimantika_101803273.egg-info/dependency_links.txt
TOPSIS_Shimantika_101803273.egg-info/entry_points.txt
TOPSIS_Shimantika_101803273.egg-info/requires.txt
TOPSIS_Shimantika_101803273.egg-info/top_level.txt
src/topsis.py